bom_analysis/__init__.py
bom_analysis/base.py
bom_analysis/bom.py
bom_analysis/build.py
bom_analysis/materials.py
bom_analysis/parameters.py
bom_analysis/parsers.py
bom_analysis/solver.py
bom_analysis/utils.py
bom_analysis-1.0.0.dist-info/LICENSE
bom_analysis-1.0.0.dist-info/METADATA
bom_analysis-1.0.0.dist-info/WHEEL
bom_analysis-1.0.0.dist-info/top_level.txt
bom_analysis-1.0.0.dist-info/RECORD
