Metadata-Version: 2.1
Name: bom-analysis
Version: 1.0.0
Summary: A framework for performing analysis based on a Bill of Materials (BOM) structure
Home-page: https://github.com/ukaea/bom_analysis
Author: UK Atomic Energy Authority
Maintainer: Sam Merriman
Maintainer-email: samuel.merriman@hotmail.co.uk
License: BSD 3-Clause “New” or “Revised” License
Classifier: License :: OSI Approved :: BSD License
Requires-Python: >=3.6
License-File: LICENSE
Requires-Dist: numpy
Requires-Dist: pint
Requires-Dist: pandas
Requires-Dist: tabulate
Requires-Dist: CoolProp
Requires-Dist: treelib
Requires-Dist: python-box
Requires-Dist: pre-commit
